CHANGES.rst
LICENSE
MANIFEST.in
README.rst
setup.py
test_verkkomaksut.py
verkkomaksut/__init__.py
verkkomaksut.egg-info/PKG-INFO
verkkomaksut.egg-info/SOURCES.txt
verkkomaksut.egg-info/dependency_links.txt
verkkomaksut.egg-info/not-zip-safe
verkkomaksut.egg-info/requires.txt
verkkomaksut.egg-info/top_level.txt