Metadata-Version: 1.1
Name: verkkomaksut
Version: 0.2.0
Summary: Python wrapper for the JSON API of Suomen Verkkomaksut.
Home-page: http://github.com/fastmonkeys/python-verkkomaksut
Author: Janne Vanhala
Author-email: janne@fastmonkeys.com
License: BSD
Platform: any
Classifier: Development Status :: 4 - Beta
Classifier: Intended Audience :: Developers
Classifier: License :: OSI Approved :: BSD License
Classifier: Operating System :: OS Independent
Classifier: Programming Language :: Python
Classifier: Topic :: Software Development :: Libraries :: Python Modules
